woohoo_pdns_gui/__init__.py
woohoo_pdns_gui/app.py
woohoo_pdns_gui/config.py
woohoo_pdns_gui/meta.py
woohoo_pdns_gui-2019.1.0.dist-info/LICENSE
woohoo_pdns_gui-2019.1.0.dist-info/METADATA
woohoo_pdns_gui-2019.1.0.dist-info/WHEEL
woohoo_pdns_gui-2019.1.0.dist-info/top_level.txt
woohoo_pdns_gui-2019.1.0.dist-info/RECORD
