Metadata-Version: 2.1
Name: woohoo-pdns-gui
Version: 2019.1.0
Summary: Web GUI for pDNS
Home-page: https://gitlab.com/scherand/woohoo-pdns-gui
Author: Andreas Scherrer
Author-email: andreas@scherrer.io
License: MIT License
Project-URL: Bug Tracker, https://gitlab.com/scherand/woohoo-pdns-gui/issues
Project-URL: Documentation, https://woohoo-pdns-gui.readthedocs.io
Project-URL: Source Code, https://gitlab.com/scherand/woohoo-pdns-gui
Platform: UNKNOWN
Classifier: Programming Language :: Python :: 3
Classifier: Programming Language :: Python :: 3.6
Classifier: License :: OSI Approved :: MIT License
Classifier: Development Status :: 4 - Beta
Requires-Dist: flask (~=1.1.1)
Requires-Dist: gunicorn (~=19.9.0)
Requires-Dist: sphinx (~=2.1.2)
